{
  "uid": "f25c18a0f6b7fbf1d8c8cedad9d564b680cce8ff52ae8a40cfc7622f04b59bb6",
  "run_id": "ucv_async_pipeline_20260131",
  "scraped_at": "2026-01-31T14:02:11.721131Z",
  "source_url": "http://ie.ucv.ro/index.php/ro/admitereh",
  "content_hash": "9d864201d93832350d9f02941085dc5ea95e716df01aca69b249f4a69afe7501",
  "entity_type": "program",
  "name": "Echipamente și Instalații de Aviație – 30 locuri buget + 6 locuri taxă",
  "faculty_uid": "4c1ddbf069252b295cfe65c0e6dc6ead6f7aa8601fe19fccefe9a118cc8b4b1c",
  "faculty_slug": "ie",
  "level": "Master",
  "duration_years": "2 ani",
  "program_id": null,
  "language": "Romanian",
  "keywords": [],
  "text_for_embedding": null,
  "admission_year": null,
  "spots_budget": 30,
  "spots_tax": 6,
  "spots_raw": "Echipamente și Instalații de Aviație – 30 locuri buget + 6 locuri taxă",
  "source_type": "html_text_parsed",
  "accuracy_confidence": 0.8,
  "last_admission_grade": null,
  "raw_admission_text": null,
  "evidence": {}
}